COPYING
COPYING.lesser
MANIFEST.in
NOTICE
README.md
requirements.txt
setup.py
Botify/__init__.py
Botify/client.py
Botify/dispatcher.py
Botify/emoji.py
Botify/file_id.py
Botify/filters.py
Botify/mime_types.py
Botify/py.typed
Botify/sync.py
Botify/utils.py
Botify/connection/__init__.py
Botify/connection/connection.py
Botify/connection/transport/__init__.py
Botify/connection/transport/tcp/__init__.py
Botify/connection/transport/tcp/tcp.py
Botify/connection/transport/tcp/tcp_abridged.py
Botify/connection/transport/tcp/tcp_abridged_o.py
Botify/connection/transport/tcp/tcp_full.py
Botify/connection/transport/tcp/tcp_intermediate.py
Botify/connection/transport/tcp/tcp_intermediate_o.py
Botify/crypto/__init__.py
Botify/crypto/aes.py
Botify/crypto/mtproto.py
Botify/crypto/prime.py
Botify/crypto/rsa.py
Botify/enums/__init__.py
Botify/enums/auto_name.py
Botify/enums/chat_action.py
Botify/enums/chat_event_action.py
Botify/enums/chat_member_status.py
Botify/enums/chat_members_filter.py
Botify/enums/chat_type.py
Botify/enums/message_entity_type.py
Botify/enums/message_media_type.py
Botify/enums/message_service_type.py
Botify/enums/messages_filter.py
Botify/enums/next_code_type.py
Botify/enums/parse_mode.py
Botify/enums/poll_type.py
Botify/enums/sent_code_type.py
Botify/enums/user_status.py
Botify/errors/__init__.py
Botify/errors/rpc_error.py
Botify/handlers/__init__.py
Botify/handlers/callback_query_handler.py
Botify/handlers/chat_join_request_handler.py
Botify/handlers/chat_member_updated_handler.py
Botify/handlers/chosen_inline_result_handler.py
Botify/handlers/deleted_messages_handler.py
Botify/handlers/disconnect_handler.py
Botify/handlers/edited_message_handler.py
Botify/handlers/handler.py
Botify/handlers/inline_query_handler.py
Botify/handlers/message_handler.py
Botify/handlers/poll_handler.py
Botify/handlers/raw_update_handler.py
Botify/handlers/user_status_handler.py
Botify/methods/__init__.py
Botify/methods/advanced/__init__.py
Botify/methods/advanced/invoke.py
botify_tg.egg-info/PKG-INFO
botify_tg.egg-info/SOURCES.txt
botify_tg.egg-info/dependency_links.txt
botify_tg.egg-info/not-zip-safe
botify_tg.egg-info/requires.txt
botify_tg.egg-info/top_level.txt
